{
  "semantics": {
    "color": {
      "palette": {
        "brand": {
          "0": {
            "value": "#000000",
            "type": "color"
          },
          "10": {
            "value": "#000965",
            "type": "color"
          },
          "20": {
            "value": "#121f8b",
            "type": "color"
          },
          "25": {
            "value": "#212d96",
            "type": "color"
          },
          "30": {
            "value": "#2e3aa2",
            "type": "color"
          },
          "35": {
            "value": "#3b47ae",
            "type": "color"
          },
          "40": {
            "value": "#4854bb",
            "type": "color"
          },
          "50": {
            "value": "#616dd6",
            "type": "color"
          },
          "60": {
            "value": "#7c88f2",
            "type": "color"
          },
          "70": {
            "value": "#9aa4ff",
            "type": "color"
          },
          "80": {
            "value": "#bdc2ff",
            "type": "color"
          },
          "85": {
            "value": "#d0d2f7",
            "type": "color"
          },
          "90": {
            "value": "#EAEAFF",
            "type": "color"
          },
          "95": {
            "value": "#F3F1FF",
            "type": "color"
          },
          "98": {
            "value": "#fbf8ff",
            "type": "color"
          },
          "99": {
            "value": "#fffbff",
            "type": "color"
          },
          "100": {
            "value": "#ffffff",
            "type": "color"
          }
        },
        "brand2": {
          "0": {
            "value": "#000000",
            "type": "color"
          },
          "10": {
            "value": "#2e1127",
            "type": "color"
          },
          "20": {
            "value": "#45263c",
            "type": "color"
          },
          "25": {
            "value": "#513148",
            "type": "color"
          },
          "30": {
            "value": "#5e3c53",
            "type": "color"
          },
          "35": {
            "value": "#6a485f",
            "type": "color"
          },
          "40": {
            "value": "#77536c",
            "type": "color"
          },
          "50": {
            "value": "#926b85",
            "type": "color"
          },
          "60": {
            "value": "#ae859f",
            "type": "color"
          },
          "70": {
            "value": "#ca9fba",
            "type": "color"
          },
          "80": {
            "value": "#e7b9d6",
            "type": "color"
          },
          "90": {
            "value": "#ffd7ef",
            "type": "color"
          },
          "95": {
            "value": "#ffecf5",
            "type": "color"
          },
          "98": {
            "value": "#fff8f9",
            "type": "color"
          },
          "99": {
            "value": "#fffbff",
            "type": "color"
          },
          "100": {
            "value": "#ffffff",
            "type": "color"
          }
        },
        "error": {
          "0": {
            "value": "#000000",
            "type": "color"
          },
          "10": {
            "value": "#410002",
            "type": "color"
          },
          "20": {
            "value": "#690005",
            "type": "color"
          },
          "25": {
            "value": "#7e0007",
            "type": "color"
          },
          "30": {
            "value": "#93000a",
            "type": "color"
          },
          "35": {
            "value": "#a80710",
            "type": "color"
          },
          "40": {
            "value": "#ba1a1a",
            "type": "color"
          },
          "50": {
            "value": "#de3730",
            "type": "color"
          },
          "60": {
            "value": "#ff5449",
            "type": "color"
          },
          "70": {
            "value": "#ff897d",
            "type": "color"
          },
          "80": {
            "value": "#ffb4ab",
            "type": "color"
          },
          "85": {
            "value": "#f6c8c5",
            "type": "color"
          },
          "90": {
            "value": "#FFE4E4",
            "type": "color"
          },
          "95": {
            "value": "#FEEDEC",
            "type": "color"
          },
          "98": {
            "value": "#FFF6F5",
            "type": "color"
          },
          "99": {
            "value": "#fffbff",
            "type": "color"
          },
          "100": {
            "value": "#ffffff",
            "type": "color"
          }
        },
        "neutral": {
          "0": {
            "value": "#000000",
            "type": "color"
          },
          "10": {
            "value": "#181B23",
            "type": "color"
          },
          "15": {
            "value": "#262C3E",
            "type": "color"
          },
          "20": {
            "value": "#323951",
            "type": "color"
          },
          "25": {
            "value": "#3D455C",
            "type": "color"
          },
          "30": {
            "value": "#50596F",
            "type": "color"
          },
          "35": {
            "value": "#5D657B",
            "type": "color"
          },
          "40": {
            "value": "#707788",
            "type": "color"
          },
          "50": {
            "value": "#888E9E",
            "type": "color"
          },
          "60": {
            "value": "#A3A9B8",
            "type": "color"
          },
          "70": {
            "value": "#D1D5DE",
            "type": "color"
          },
          "80": {
            "value": "#E2E5EA",
            "type": "color"
          },
          "85": {
            "value": "#E9EBED",
            "type": "color"
          },
          "90": {
            "value": "#F1F2F5",
            "type": "color"
          },
          "95": {
            "value": "#F5F5F8",
            "type": "color"
          },
          "98": {
            "value": "#F9F9FB",
            "type": "color"
          },
          "99": {
            "value": "#fcfcfd",
            "type": "color"
          },
          "100": {
            "value": "#ffffff",
            "type": "color"
          }
        },
        "gray": {
          "0": {
            "value": "#000000",
            "type": "color"
          },
          "10": {
            "value": "#1e1a22",
            "type": "color"
          },
          "20": {
            "value": "#342f37",
            "type": "color"
          },
          "25": {
            "value": "#3f3942",
            "type": "color"
          },
          "30": {
            "value": "#4a454d",
            "type": "color"
          },
          "35": {
            "value": "#565059",
            "type": "color"
          },
          "40": {
            "value": "#635c65",
            "type": "color"
          },
          "50": {
            "value": "#7c757e",
            "type": "color"
          },
          "60": {
            "value": "#968e98",
            "type": "color"
          },
          "70": {
            "value": "#b1a8b3",
            "type": "color"
          },
          "80": {
            "value": "#cdc4ce",
            "type": "color"
          },
          "90": {
            "value": "#e9dfea",
            "type": "color"
          },
          "95": {
            "value": "#f8eef9",
            "type": "color"
          },
          "98": {
            "value": "#fff7fe",
            "type": "color"
          },
          "99": {
            "value": "#fffbff",
            "type": "color"
          },
          "100": {
            "value": "#ffffff",
            "type": "color"
          }
        },
        "common": {
          "link": {
            "value": "#0056d0",
            "type": "color"
          },
          "visited": {
            "value": "#9A00D0",
            "type": "color"
          },
          "white": {
            "value": "#ffffff",
            "type": "color"
          },
          "black": {
            "value": "#000000",
            "type": "color"
          }
        }
      },
      "bg": {
        "light": {
          "gray": {
            "l=1": {
              "type": "color",
              "value": "{semantics.color.palette.gray.95}"
            },
            "l=2": {
              "type": "color",
              "value": "{semantics.color.palette.gray.90}"
            },
            "l=3": {
              "type": "color",
              "value": "{semantics.color.palette.gray.85}"
            },
            "l=4": {
              "type": "color",
              "value": "{semantics.color.palette.gray.80}"
            }
          },
          "neutral": {
            "l=1": {
              "type": "color",
              "value": "{semantics.color.palette.neutral.95}"
            },
            "l=2": {
              "type": "color",
              "value": "{semantics.color.palette.neutral.90}"
            },
            "l=3": {
              "type": "color",
              "value": "{semantics.color.palette.neutral.85}"
            },
            "l=4": {
              "type": "color",
              "value": "{semantics.color.palette.neutral.80}"
            }
          },
          "brand": {
            "l=1": {
              "type": "color",
              "value": "{semantics.color.palette.brand.95}"
            },
            "l=2": {
              "type": "color",
              "value": "{semantics.color.palette.brand.90}"
            },
            "l=3": {
              "type": "color",
              "value": "{semantics.color.palette.brand.85}"
            },
            "l=4": {
              "type": "color",
              "value": "{semantics.color.palette.brand.80}"
            }
          },
          "brand2": {
            "l=1": {
              "type": "color",
              "value": "{semantics.color.palette.brand2.95}"
            },
            "l=2": {
              "type": "color",
              "value": "{semantics.color.palette.brand2.90}"
            },
            "l=3": {
              "type": "color",
              "value": "{semantics.color.palette.brand2.85}"
            },
            "l=4": {
              "type": "color",
              "value": "{semantics.color.palette.brand2.80}"
            }
          },
          "error": {
            "l=1": {
              "type": "color",
              "value": "{semantics.color.palette.error.95}"
            },
            "l=2": {
              "type": "color",
              "value": "{semantics.color.palette.error.90}"
            },
            "l=3": {
              "type": "color",
              "value": "{semantics.color.palette.error.85}"
            },
            "l=4": {
              "type": "color",
              "value": "{semantics.color.palette.error.80}"
            }
          },
          "disabled": {
            "l=1": {
              "type": "color",
              "value": "{semantics.color.palette.gray.70}"
            },
            "l=2": {
              "type": "color",
              "value": "{semantics.color.palette.gray.60}"
            },
            "l=3": {
              "type": "color",
              "value": "{semantics.color.palette.gray.50}"
            },
            "l=4": {
              "type": "color",
              "value": "{semantics.color.palette.gray.40}"
            }
          }
        },
        "dark": {
          "gray": {
            "l=1": {
              "type": "color",
              "value": "{semantics.color.palette.gray.10}"
            },
            "l=2": {
              "type": "color",
              "value": "{semantics.color.palette.gray.15}"
            },
            "l=3": {
              "type": "color",
              "value": "{semantics.color.palette.gray.20}"
            },
            "l=4": {
              "type": "color",
              "value": "{semantics.color.palette.gray.25}"
            }
          },
          "neutral": {
            "l=1": {
              "type": "color",
              "value": "{semantics.color.palette.neutral.10}"
            },
            "l=2": {
              "type": "color",
              "value": "{semantics.color.palette.neutral.15}"
            },
            "l=3": {
              "type": "color",
              "value": "{semantics.color.palette.neutral.20}"
            },
            "l=4": {
              "type": "color",
              "value": "{semantics.color.palette.neutral.25}"
            }
          },
          "brand": {
            "l=1": {
              "type": "color",
              "value": "{semantics.color.palette.brand.10}"
            },
            "l=2": {
              "type": "color",
              "value": "{semantics.color.palette.brand.15}"
            },
            "l=3": {
              "type": "color",
              "value": "{semantics.color.palette.brand.20}"
            },
            "l=4": {
              "type": "color",
              "value": "{semantics.color.palette.brand.25}"
            }
          },
          "brand2": {
            "l=1": {
              "type": "color",
              "value": "{semantics.color.palette.brand2.10}"
            },
            "l=2": {
              "type": "color",
              "value": "{semantics.color.palette.brand2.15}"
            },
            "l=3": {
              "type": "color",
              "value": "{semantics.color.palette.brand2.20}"
            },
            "l=4": {
              "type": "color",
              "value": "{semantics.color.palette.brand2.25}"
            }
          },
          "error": {
            "l=1": {
              "type": "color",
              "value": "{semantics.color.palette.error.10}"
            },
            "l=2": {
              "type": "color",
              "value": "{semantics.color.palette.error.15}"
            },
            "l=3": {
              "type": "color",
              "value": "{semantics.color.palette.error.20}"
            },
            "l=4": {
              "type": "color",
              "value": "{semantics.color.palette.error.25}"
            }
          },
          "disabled": {
            "l=1": {
              "type": "color",
              "value": "{semantics.color.palette.gray.40}"
            },
            "l=2": {
              "type": "color",
              "value": "{semantics.color.palette.gray.50}"
            },
            "l=3": {
              "type": "color",
              "value": "{semantics.color.palette.gray.60}"
            },
            "l=4": {
              "type": "color",
              "value": "{semantics.color.palette.gray.70}"
            }
          }
        }
      },
      "text": {
        "onLight": {
          "gray": {
            "1st": {
              "type": "color",
              "value": "{semantics.color.palette.gray.10}"
            },
            "2nd": {
              "type": "color",
              "value": "{semantics.color.palette.gray.15}"
            },
            "3rd": {
              "type": "color",
              "value": "{semantics.color.palette.gray.20}"
            },
            "4th": {
              "type": "color",
              "value": "{semantics.color.palette.gray.25}"
            }
          },
          "neutral": {
            "1st": {
              "type": "color",
              "value": "{semantics.color.palette.neutral.10}"
            },
            "2nd": {
              "type": "color",
              "value": "{semantics.color.palette.neutral.15}"
            },
            "3rd": {
              "type": "color",
              "value": "{semantics.color.palette.neutral.20}"
            },
            "4th": {
              "type": "color",
              "value": "{semantics.color.palette.neutral.25}"
            }
          },
          "brand": {
            "1st": {
              "type": "color",
              "value": "{semantics.color.palette.brand.10}"
            },
            "2nd": {
              "type": "color",
              "value": "{semantics.color.palette.brand.15}"
            },
            "3rd": {
              "type": "color",
              "value": "{semantics.color.palette.brand.20}"
            },
            "4th": {
              "type": "color",
              "value": "{semantics.color.palette.brand.25}"
            }
          },
          "brand2": {
            "1st": {
              "type": "color",
              "value": "{semantics.color.palette.brand2.10}"
            },
            "2nd": {
              "type": "color",
              "value": "{semantics.color.palette.brand2.15}"
            },
            "3rd": {
              "type": "color",
              "value": "{semantics.color.palette.brand2.20}"
            },
            "4th": {
              "type": "color",
              "value": "{semantics.color.palette.brand2.25}"
            }
          },
          "error": {
            "1st": {
              "type": "color",
              "value": "{semantics.color.palette.error.10}"
            },
            "2nd": {
              "type": "color",
              "value": "{semantics.color.palette.error.15}"
            },
            "3rd": {
              "type": "color",
              "value": "{semantics.color.palette.error.20}"
            },
            "4th": {
              "type": "color",
              "value": "{semantics.color.palette.error.25}"
            }
          },
          "disabled": {
            "1st": {
              "type": "color",
              "value": "{semantics.color.palette.gray.40}"
            },
            "2nd": {
              "type": "color",
              "value": "{semantics.color.palette.gray.50}"
            },
            "3rd": {
              "type": "color",
              "value": "{semantics.color.palette.gray.60}"
            },
            "4th": {
              "type": "color",
              "value": "{semantics.color.palette.gray.70}"
            }
          }
        },
        "onDark": {
          "gray": {
            "1st": {
              "type": "color",
              "value": "{semantics.color.palette.gray.95}"
            },
            "2nd": {
              "type": "color",
              "value": "{semantics.color.palette.gray.90}"
            },
            "3rd": {
              "type": "color",
              "value": "{semantics.color.palette.gray.85}"
            },
            "4th": {
              "type": "color",
              "value": "{semantics.color.palette.gray.80}"
            }
          },
          "neutral": {
            "1st": {
              "type": "color",
              "value": "{semantics.color.palette.neutral.95}"
            },
            "2nd": {
              "type": "color",
              "value": "{semantics.color.palette.neutral.90}"
            },
            "3rd": {
              "type": "color",
              "value": "{semantics.color.palette.neutral.85}"
            },
            "4th": {
              "type": "color",
              "value": "{semantics.color.palette.neutral.80}"
            }
          },
          "brand": {
            "1st": {
              "type": "color",
              "value": "{semantics.color.palette.brand.95}"
            },
            "2nd": {
              "type": "color",
              "value": "{semantics.color.palette.brand.90}"
            },
            "3rd": {
              "type": "color",
              "value": "{semantics.color.palette.brand.85}"
            },
            "4th": {
              "type": "color",
              "value": "{semantics.color.palette.brand.80}"
            }
          },
          "brand2": {
            "1st": {
              "type": "color",
              "value": "{semantics.color.palette.brand2.95}"
            },
            "2nd": {
              "type": "color",
              "value": "{semantics.color.palette.brand2.90}"
            },
            "3rd": {
              "type": "color",
              "value": "{semantics.color.palette.brand2.85}"
            },
            "4th": {
              "type": "color",
              "value": "{semantics.color.palette.brand2.80}"
            }
          },
          "error": {
            "1st": {
              "type": "color",
              "value": "{semantics.color.palette.error.95}"
            },
            "2nd": {
              "type": "color",
              "value": "{semantics.color.palette.error.90}"
            },
            "3rd": {
              "type": "color",
              "value": "{semantics.color.palette.error.85}"
            },
            "4th": {
              "type": "color",
              "value": "{semantics.color.palette.error.80}"
            }
          },
          "disabled": {
            "1st": {
              "type": "color",
              "value": "{semantics.color.palette.gray.70}"
            },
            "2nd": {
              "type": "color",
              "value": "{semantics.color.palette.gray.60}"
            },
            "3rd": {
              "type": "color",
              "value": "{semantics.color.palette.gray.50}"
            },
            "4th": {
              "type": "color",
              "value": "{semantics.color.palette.gray.40}"
            }
          }
        }
      },
      "accents": {
        "onLight": {
          "brand": {
            "weaker": {
              "type": "color",
              "value": "{semantics.color.palette.brand.60}"
            },
            "default": {
              "type": "color",
              "value": "{semantics.color.palette.brand.50}"
            },
            "stronger": {
              "type": "color",
              "value": "{semantics.color.palette.brand.40}"
            }
          },
          "brand2": {
            "weaker": {
              "type": "color",
              "value": "{semantics.color.palette.brand2.60}"
            },
            "default": {
              "type": "color",
              "value": "{semantics.color.palette.brand2.50}"
            },
            "stronger": {
              "type": "color",
              "value": "{semantics.color.palette.brand2.40}"
            }
          },
          "error": {
            "weaker": {
              "type": "color",
              "value": "{semantics.color.palette.error.60}"
            },
            "default": {
              "type": "color",
              "value": "{semantics.color.palette.error.50}"
            },
            "stronger": {
              "type": "color",
              "value": "{semantics.color.palette.error.40}"
            }
          }
        },
        "onDark": {
          "brand": {
            "weaker": {
              "type": "color",
              "value": "{semantics.color.palette.brand.60}"
            },
            "default": {
              "type": "color",
              "value": "{semantics.color.palette.brand.50}"
            },
            "stronger": {
              "type": "color",
              "value": "{semantics.color.palette.brand.40}"
            }
          },
          "brand2": {
            "weaker": {
              "type": "color",
              "value": "{semantics.color.palette.brand2.60}"
            },
            "default": {
              "type": "color",
              "value": "{semantics.color.palette.brand2.50}"
            },
            "stronger": {
              "type": "color",
              "value": "{semantics.color.palette.brand2.40}"
            }
          },
          "error": {
            "weaker": {
              "type": "color",
              "value": "{semantics.color.palette.error.60}"
            },
            "default": {
              "type": "color",
              "value": "{semantics.color.palette.error.50}"
            },
            "stronger": {
              "type": "color",
              "value": "{semantics.color.palette.error.40}"
            }
          }
        }
      }
    }
  }
}